{
  "providers": {
    "awscloudformation": {
      "AuthRoleName": "amplify-braveapp-prod-115121-authRole",
      "UnauthRoleArn": "arn:aws:iam::348692145831:role/amplify-braveapp-prod-115121-unauthRole",
      "AuthRoleArn": "arn:aws:iam::348692145831:role/amplify-braveapp-prod-115121-authRole",
      "Region": "us-east-2",
      "DeploymentBucketName": "amplify-braveapp-prod-115121-deployment",
      "UnauthRoleName": "amplify-braveapp-prod-115121-unauthRole",
      "StackName": "amplify-braveapp-prod-115121",
      "StackId": "arn:aws:cloudformation:us-east-2:348692145831:stack/amplify-braveapp-prod-115121/95256f90-9964-11eb-a7f9-02f96f814c7e",
      "AmplifyAppId": "d3fcj5js8se5t3"
    }
  },
  "auth": {
    "braveapp0ea8ea07": {
      "service": "Cognito",
      "providerPlugin": "awscloudformation",
      "dependsOn": [],
      "customAuth": false,
      "output": {
        "UserPoolId": "us-east-2_beTcykTM9",
        "AppClientIDWeb": "5ig184k6ps2qf7577g2qnk4mjl",
        "AppClientID": "1isj7pi952benpu937pqdm57st",
        "HostedUIDomain": "braveappa3b93ee9-a3b93ee9-dev",
        "IdentityPoolId": "us-east-2:69169c15-c0c4-4e0b-886c-4afab307e612",
        "IdentityPoolName": "braveapp0ea8ea07_identitypool_0ea8ea07__dev",
        "OAuthMetadata": "{\"AllowedOAuthFlows\":[\"code\"],\"AllowedOAuthScopes\":[\"phone\",\"email\",\"openid\",\"profile\",\"aws.cognito.signin.user.admin\"],\"CallbackURLs\":[\"http://localhost:4200/\",\"https://app.brave.credit/\"],\"LogoutURLs\":[\"http://localhost:4200/\",\"https://app.brave.credit/\"]}",
        "UserPoolName": "braveapp0ea8ea07_userpool_0ea8ea07"
      },
      "lastPushTimeStamp": "2021-05-25T21:36:55.331Z",
      "providerMetadata": {
        "s3TemplateURL": "https://s3.amazonaws.com/amplify-braveapp-prod-115121-deployment/amplify-cfn-templates/auth/braveapp0ea8ea07-cloudformation-template.yml",
        "logicalId": "authbraveapp0ea8ea07"
      },
      "lastPushTimeStamp": "2021-04-09T18:58:38.966Z",
      "output": {
        "UserPoolId": "us-east-2_R22DawoAR",
        "AppClientIDWeb": "rpqo3q7uaftlr8rp39kfvh08t",
        "AppClientID": "rqsijcgu9ilsu9t0bq42tgh38",
        "IdentityPoolId": "us-east-2:ea31caf7-0945-4607-a3c4-0c9942967a32",
        "IdentityPoolName": "braveapp0ea8ea07_identitypool_0ea8ea07__prod",
        "UserPoolName": "braveapp0ea8ea07_userpool_0ea8ea07"
      },
      "lastPushDirHash": "LMXK8MOCvt4tU5EJRMJVMY+FREM="
    }
  },
  "api": {
    "braveapp": {
      "service": "AppSync",
      "providerPlugin": "awscloudformation",
      "output": {
        "authConfig": {
          "defaultAuthentication": {
            "authenticationType": "AMAZON_COGNITO_USER_POOLS",
            "userPoolConfig": {
              "userPoolId": "authbraveapp0ea8ea07"
            }
          },
          "additionalAuthenticationProviders": []
        },
        "GraphQLAPIIdOutput": "4tpaga7rzjayhk75opsmpeurme",
        "GraphQLAPIEndpointOutput": "https://krybm5pc3nbgdk4zwgcva2i4va.appsync-api.us-east-2.amazonaws.com/graphql"
      },
      "lastPushTimeStamp": "2021-05-25T21:36:55.331Z",
      "providerMetadata": {
        "s3TemplateURL": "https://s3.amazonaws.com/amplify-braveapp-prod-115121-deployment/amplify-cfn-templates/api/cloudformation-template.json",
        "logicalId": "apibraveapp"
      },
      "lastPushTimeStamp": "2021-04-09T18:58:38.966Z",
      "lastPushDirHash": "4mApqlb2MluMJJV3bLy/edwg+40="
    }
  },
  "function": {
    "S3Trigger3c67af6a": {
      "service": "Lambda",
      "providerPlugin": "awscloudformation",
      "build": true,
      "lastBuildTimeStamp": "2021-04-09T18:53:07.631Z",
      "lastPackageTimeStamp": "2021-04-09T18:53:07.742Z",
      "distZipFilename": "S3Trigger3c67af6a-7979447a614d7439396a-build.zip",
      "s3Bucket": {
        "deploymentBucketName": "amplify-braveapp-prod-115121-deployment",
        "s3Key": "amplify-builds/S3Trigger3c67af6a-7979447a614d7439396a-build.zip"
      },
      "lastPushTimeStamp": "2021-05-25T21:36:55.331Z",
      "providerMetadata": {
        "s3TemplateURL": "https://s3.amazonaws.com/amplify-braveapp-prod-115121-deployment/amplify-cfn-templates/function/S3Trigger3c67af6a-cloudformation-template.json",
        "logicalId": "functionS3Trigger3c67af6a"
      },
      "lastPushTimeStamp": "2021-04-09T18:58:38.966Z",
      "output": {
        "Region": "us-east-2",
        "Arn": "arn:aws:lambda:us-east-2:348692145831:function:S3Trigger3c67af6a-prod",
        "Name": "S3Trigger3c67af6a-prod",
        "LambdaExecutionRole": "S3Trigger3c67af6aLambdaRole3c67af6a-prod"
      },
      "lastBuildTimeStamp": "2021-05-25T21:36:55.085Z",
      "lastPackageTimeStamp": "2021-05-25T21:36:55.111Z",
      "distZipFilename": "S3Trigger3c67af6a-7979447a614d7439396a-build.zip",
      "lastPushDirHash": "SmDX3G8HbfF/Ow/o98e1rbNltS0="
    }
  },
  "storage": {
    "s3b5dd189d": {
      "service": "S3",
      "providerPlugin": "awscloudformation",
      "dependsOn": [
        {
          "category": "function",
          "resourceName": "S3Trigger3c67af6a",
          "attributes": [
            "Name",
            "Arn",
            "LambdaExecutionRole"
          ]
        }
      ],
      "output": {
        "BucketName": "braveapp7123270838f144d09004f496c2f9ef0f110519-dev",
        "Region": "us-east-2"
      },
      "lastPushTimeStamp": "2021-05-25T21:36:55.331Z",
      "providerMetadata": {
        "s3TemplateURL": "https://s3.amazonaws.com/amplify-braveapp-prod-115121-deployment/amplify-cfn-templates/storage/s3-cloudformation-template.json",
        "logicalId": "storages3b5dd189d"
      },
      "lastPushTimeStamp": "2021-04-09T18:58:38.966Z",
      "output": {
        "BucketName": "braveapp7123270838f144d09004f496c2f9ef0f115121-prod",
        "Region": "us-east-2"
      },
      "lastPushDirHash": "RiWbI0UmpfYFTrOVWAwaWwiqUao="
    }
  }
}